{"title":"Combined feed","url":"https://MusicReleaseKR.github.io/vibe/all.xml","elements":[{"title":"CLICHÉ (네이버 바이브 ─ 최신앨범 ─ 국내)","contents":"적재","link":"https://vibe.naver.com/album/32239229","retrieved":1730193352629},{"title":"finstagram (네이버 바이브 ─ 최신앨범 ─ 국내)","contents":"OLNL (오르내림)","link":"https://vibe.naver.com/album/32238804","retrieved":1730193352629},{"title":"스테이지 파이터(STF) Original Vol.4 (네이버 바이브 ─ 최신앨범 ─ 국내)","contents":"<div data-v-78809b3d=\"\" class=\"\" data-v-4639e6ee=\"\"><div data-v-78809b3d=\"\" class=\"thumb_area\"><a data-v-78809b3d=\"\" href=\"/album/32239106\" class=\"link\"><img data-v-cbb0f7a8=\"\" data-v-78809b3d=\"\" src=\"https://musicmeta-phinf.pstatic.net/album/032/239/32239106.jpg?type=r360Fll&amp;v=20241028170906\" class=\"thumb v-lazy-image v-lazy-image-loaded\" alt=\"스테이지 파이터(STF) Original Vol.4 앨범 커버\"><!----><!----></a><a data-v-5e072f9e=\"\" data-v-78809b3d=\"\" href=\"#\" role=\"button\" screen-reader-live=\"\" class=\"btn_play_now\" aria-describedby=\"32239106\"><span data-v-5e072f9e=\"\" class=\"blind\">재생하기</span><!----></a><div data-v-78809b3d=\"\" class=\"more_option only\"><!----><div data-v-18500bfa=\"\" class=\"dropdown_wrap\"><a data-v-18500bfa=\"\" href=\"#\" role=\"button\" aria-haspopup=\"menu\" aria-expanded=\"false\" aria-describedby=\"32239106\" class=\"btn_option_now\"><span data-v-18500bfa=\"\" class=\"blind\">옵션 보기</span></a><div data-v-18500bfa=\"\" role=\"menu\" class=\"playable_dropdown\" style=\"display: none;\"><!----><!----><a data-v-18500bfa=\"\" href=\"#\" role=\"button\" class=\"dropdown_item dropdown_playlist_add\">내 플레이리스트 추가</a><a data-v-18500bfa=\"\" href=\"#\" role=\"button\" class=\"dropdown_item dropdown_like\"><span data-v-18500bfa=\"\">좋아요</span></a><a data-v-18500bfa=\"\" href=\"#\" role=\"button\" class=\"dropdown_item dropdown_add_next\">바로 다음에 추가</a><a data-v-18500bfa=\"\" href=\"#\" role=\"button\" class=\"dropdown_item dropdown_add_last\">맨 아래에 추가</a><a data-v-682dad78=\"\" href=\"#\" role=\"button\" aria-haspopup=\"dialog\" class=\"dropdown_item dropdown_mp3\" data-v-18500bfa=\"\"><span data-v-682dad78=\"\" class=\"\"> MP3 구매 <!----></span></a><a data-v-18500bfa=\"\" href=\"#\" data-style=\"unity-v2\" data-oninitialize=\"window.__splugin_oninitialize()\" data-url=\"https://vibe.naver.com/album/32239106\" data-title=\"스테이지 파이터(STF) Original Vol.4\" class=\"naver-splugin spi_sns_share dropdown_share\">공유</a><!----><div data-v-18500bfa=\"\" class=\"btn_close_area\"><a data-v-18500bfa=\"\" href=\"#\" class=\"btn_close\"><span data-v-18500bfa=\"\" class=\"blind\">모달 닫기</span></a></div></div></div></div></div><div data-v-78809b3d=\"\" class=\"info\"><!----><a data-v-78809b3d=\"\" href=\"/album/32239106\" class=\"title\"><span data-v-78809b3d=\"\" class=\"text_wrap\"><span data-v-78809b3d=\"\" id=\"32239106\" class=\"text\">스테이지 파이터(STF) Original Vol.4</span><!----><!----></span><span data-v-78809b3d=\"\" class=\"blind\">페이지로 이동</span></a><div data-v-78809b3d=\"\" class=\"artist\"><span data-v-78809b3d=\"\" class=\"artist_sub_inner\"><span><span class=\"link_artist\">Various Artists</span><!----></span></span><span data-v-78809b3d=\"\" class=\"blind\">아티스트명</span></div></div></div>","link":"https://vibe.naver.com/album/32239106","retrieved":1730193352620},{"title":"내 마음을 뺏는 건 (네이버 바이브 ─ 최신앨범 ─ 국내)","contents":"송하예","link":"https://vibe.naver.com/album/32239094","retrieved":1730193352640},{"title":"솔라감성 Part 8 (네이버 바이브 ─ 최신앨범 ─ 국내)","contents":"솔라(마마무)","link":"https://vibe.naver.com/album/32239170","retrieved":1730193352642},{"title":"ONE (네이버 바이브 ─ 최신앨범 ─ 국내)","contents":"blah","link":"https://vibe.naver.com/album/32238886","retrieved":1730193352642},{"title":"Branding (네이버 바이브 ─ 최신앨범 ─ 국내)","contents":"스케리피(Scary'P)","link":"https://vibe.naver.com/album/32240597","retrieved":1730193352642},{"title":"나침반 (네이버 바이브 ─ 최신앨범 ─ 국내)","contents":"한로로","link":"https://vibe.naver.com/album/32238818","retrieved":1730193352642},{"title":"있어주라 (네이버 바이브 ─ 최신앨범 ─ 국내)","contents":"권지은","link":"https://vibe.naver.com/album/32238825","retrieved":1730193352642},{"title":"What Is Your Phone Number (네이버 바이브 ─ 최신앨범 ─ 국내)","contents":"oid(오이드)","link":"https://vibe.naver.com/album/32239102","retrieved":1730193352642},{"title":"THE BOYZ 9th MINI ALBUM [導火線] (네이버 바이브 ─ 최신앨범 ─ 국내)","contents":"더보이즈(THE BOYZ)","link":"https://vibe.naver.com/album/32238726","retrieved":1730106994898},{"title":"LOVEE (네이버 바이브 ─ 최신앨범 ─ 국내)","contents":"Wynn(윈)","link":"https://vibe.naver.com/album/32238822","retrieved":1730172117788},{"title":"변하지 않을 멜로디 (Feat. JAEHA) (네이버 바이브 ─ 최신앨범 ─ 국내)","contents":"Youngcode","link":"https://vibe.naver.com/album/32239122","retrieved":1730172117788},{"title":"San Diego Blues (네이버 바이브 ─ 최신앨범 ─ 국내)","contents":"Austn(오스틴)","link":"https://vibe.naver.com/album/32239099","retrieved":1730172117788},{"title":"컬러링 '야야야' (원곡 베이비복스) (네이버 바이브 ─ 최신앨범 ─ 국내)","contents":"D2ear","link":"https://vibe.naver.com/album/32239090","retrieved":1730172117788},{"title":"눈에 보이지 않는 노래는 (네이버 바이브 ─ 최신앨범 ─ 국내)","contents":"연정(YEONJEONG)","link":"https://vibe.naver.com/album/32239168","retrieved":1730172117800},{"title":"사랑이라 말했던 너의 모든 순간들이 (네이버 바이브 ─ 최신앨범 ─ 국내)","contents":"양하진","link":"https://vibe.naver.com/album/32239566","retrieved":1730172117800},{"title":"ONCE AGAIN (네이버 바이브 ─ 최신앨범 ─ 국내)","contents":"이재원","link":"https://vibe.naver.com/album/32238955","retrieved":1730172117800},{"title":"Luv tape (네이버 바이브 ─ 최신앨범 ─ 국내)","contents":"리플리(RIPLEY)","link":"https://vibe.naver.com/album/32239140","retrieved":1730172117800},{"title":"Dream of You (Korean Ver.) (네이버 바이브 ─ 최신앨범 ─ 국내)","contents":"SCOOL","link":"https://vibe.naver.com/album/32238869","retrieved":1730172117800},{"title":"꽃샘추위 주의보 (네이버 바이브 ─ 최신앨범 ─ 국내)","contents":"이을 (E.ul)","link":"https://vibe.naver.com/album/32239022","retrieved":1730172117800},{"title":"East Side West Side (네이버 바이브 ─ 최신앨범 ─ 국내)","contents":"Jiho Givenchy(지호지방시)","link":"https://vibe.naver.com/album/32239101","retrieved":1730172117800},{"title":"꿈 속에서 난 나방이었어 (네이버 바이브 ─ 최신앨범 ─ 국내)","contents":"김새얀","link":"https://vibe.naver.com/album/32239119","retrieved":1730172117800},{"title":"컬러링 '사랑이라는 이유로' (원곡 김광석) (네이버 바이브 ─ 최신앨범 ─ 국내)","contents":"현모","link":"https://vibe.naver.com/album/32238779","retrieved":1730172117800},{"title":"니가 보고 싶어져 (네이버 바이브 ─ 최신앨범 ─ 국내)","contents":"케이플라워(K. Flower)","link":"https://vibe.naver.com/album/32239049","retrieved":1730172117800},{"title":"오랜만이야 (네이버 바이브 ─ 최신앨범 ─ 국내)","contents":"Inf","link":"https://vibe.naver.com/album/32238948","retrieved":1730172117800},{"title":"Make you feel my heart (네이버 바이브 ─ 최신앨범 ─ 국내)","contents":"Dj.Girin","link":"https://vibe.naver.com/album/32239112","retrieved":1730172117800},{"title":"링링 (네이버 바이브 ─ 최신앨범 ─ 국내)","contents":"채은정","link":"https://vibe.naver.com/album/32239053","retrieved":1730172117803},{"title":"Day 1 (Feat. TRADE L, Gist) (네이버 바이브 ─ 최신앨범 ─ 국내)","contents":"Modern IVY","link":"https://vibe.naver.com/album/32239061","retrieved":1730172117803},{"title":"한 번 더 그날이 오면 (네이버 바이브 ─ 최신앨범 ─ 국내)","contents":"한경일","link":"https://vibe.naver.com/album/32238962","retrieved":1730172117803},{"title":"뻔한 영화 (네이버 바이브 ─ 최신앨범 ─ 국내)","contents":"AUBE(오브)","link":"https://vibe.naver.com/album/32239116","retrieved":1730172117803},{"title":"모난 마음 (네이버 바이브 ─ 최신앨범 ─ 국내)","contents":"경이","link":"https://vibe.naver.com/album/32238842","retrieved":1730172117803},{"title":"이 밤 (네이버 바이브 ─ 최신앨범 ─ 국내)","contents":"Mooni","link":"https://vibe.naver.com/album/32239095","retrieved":1730172117803},{"title":"746 - The 1st Album (네이버 바이브 ─ 최신앨범 ─ 국내)","contents":"최유리","link":"https://vibe.naver.com/album/32121906","retrieved":1730106994898},{"title":"Passion Of Various Types (네이버 바이브 ─ 최신앨범 ─ 국내)","contents":"Low Hanging Fruits","link":"https://vibe.naver.com/album/32238602","retrieved":1730106994898},{"title":"그냥 사랑이 식었다고 말하지 그랬어 (네이버 바이브 ─ 최신앨범 ─ 국내)","contents":"이소정","link":"https://vibe.naver.com/album/32236174","retrieved":1730106994898},{"title":"SHINE (네이버 바이브 ─ 최신앨범 ─ 국내)","contents":"손태진","link":"https://vibe.naver.com/album/32238855","retrieved":1730106994899},{"title":"마치 사랑처럼 (네이버 바이브 ─ 최신앨범 ─ 국내)","contents":"자정","link":"https://vibe.naver.com/album/32238280","retrieved":1730106994904},{"title":"Cherish (My Love) (Remixes) (네이버 바이브 ─ 최신앨범 ─ 국내)","contents":"아일릿(ILLIT)","link":"https://vibe.naver.com/album/32236199","retrieved":1730106994904},{"title":"다시 사랑할 용기 (네이버 바이브 ─ 최신앨범 ─ 국내)","contents":"우이경","link":"https://vibe.naver.com/album/32235876","retrieved":1730106994904},{"title":"Loving You (네이버 바이브 ─ 최신앨범 ─ 국내)","contents":"LEEYOUNGWOONG","link":"https://vibe.naver.com/album/32236073","retrieved":1730106994904},{"title":"kin (네이버 바이브 ─ 최신앨범 ─ 국내)","contents":"비공정","link":"https://vibe.naver.com/album/32238775","retrieved":1730106994904},{"title":"월간 AP - 2024년 10월 (네이버 바이브 ─ 최신앨범 ─ 국내)","contents":"에이피 알케미(AP Alchemy)","link":"https://vibe.naver.com/album/32236564","retrieved":1730106994904},{"title":"살아남아(remix) (네이버 바이브 ─ 최신앨범 ─ 국내)","contents":"Odd95","link":"https://vibe.naver.com/album/32236525","retrieved":1730106994906},{"title":"산책 (네이버 바이브 ─ 최신앨범 ─ 국내)","contents":"김동률","link":"https://vibe.naver.com/album/32236187","retrieved":1730020443597},{"title":"Goodbye (네이버 바이브 ─ 최신앨범 ─ 국내)","contents":"406호 프로젝트","link":"https://vibe.naver.com/album/32236178","retrieved":1730085898453},{"title":"Everything Bagel (네이버 바이브 ─ 최신앨범 ─ 국내)","contents":"차울","link":"https://vibe.naver.com/album/32238603","retrieved":1730085898453},{"title":"illusion (네이버 바이브 ─ 최신앨범 ─ 국내)","contents":"H3ATHR SUN(헤더썬)","link":"https://vibe.naver.com/album/32236182","retrieved":1730085898461},{"title":"Art Factory (네이버 바이브 ─ 최신앨범 ─ 국내)","contents":"SÉON(세온)","link":"https://vibe.naver.com/album/32236527","retrieved":1730085898488},{"title":"아직 그대론데 (네이버 바이브 ─ 최신앨범 ─ 국내)","contents":"란(RAN)","link":"https://vibe.naver.com/album/32236461","retrieved":1730085898488},{"title":"Heart Of A Woman (네이버 바이브 ─ 최신앨범 ─ 해외)","contents":"Summer Walker","link":"https://vibe.naver.com/album/32232047","retrieved":1730172125111},{"title":"Magpie (네이버 바이브 ─ 최신앨범 ─ 해외)","contents":"Peach pit","link":"https://vibe.naver.com/album/32232655","retrieved":1730172125111},{"title":"Loveland (네이버 바이브 ─ 최신앨범 ─ 해외)","contents":"Fly By Midnight","link":"https://vibe.naver.com/album/32231976","retrieved":1730172125113},{"title":"wasn't a fighting kid (네이버 바이브 ─ 최신앨범 ─ 해외)","contents":"Thomas Headon","link":"https://vibe.naver.com/album/32232151","retrieved":1730172125113},{"title":"Symphony of Lungs - BBC Proms at the Royal Albert Hall (네이버 바이브 ─ 최신앨범 ─ 해외)","contents":"Florence + The Machine","link":"https://vibe.naver.com/album/32230746","retrieved":1730172125113},{"title":"YOUR WAY'S BETTER (네이버 바이브 ─ 최신앨범 ─ 해외)","contents":"Forrest Frank","link":"https://vibe.naver.com/album/32235893","retrieved":1730172125113},{"title":"Two Shades Blonder (네이버 바이브 ─ 최신앨범 ─ 해외)","contents":"Devon Cole","link":"https://vibe.naver.com/album/32232691","retrieved":1730172125113},{"title":"No Pressure (네이버 바이브 ─ 최신앨범 ─ 해외)","contents":"KnowKnow","link":"https://vibe.naver.com/album/32238123","retrieved":1730172125113},{"title":"A Christmas Album (네이버 바이브 ─ 최신앨범 ─ 해외)","contents":"Matthew Ifield","link":"https://vibe.naver.com/album/32232045","retrieved":1730172125113},{"title":"LL (네이버 바이브 ─ 최신앨범 ─ 해외)","contents":"The Hellp","link":"https://vibe.naver.com/album/32233330","retrieved":1730172125113},{"title":"Between Us (네이버 바이브 ─ 최신앨범 ─ 해외)","contents":"Alex Martura","link":"https://vibe.naver.com/album/32239055","retrieved":1730172125113},{"title":"Work It Out (Deleasa Remix) (네이버 바이브 ─ 최신앨범 ─ 해외)","contents":"Joe Jonas","link":"https://vibe.naver.com/album/32230827","retrieved":1730172125114},{"title":"Flower of the soul (full bloom) (네이버 바이브 ─ 최신앨범 ─ 해외)","contents":"liana flores","link":"https://vibe.naver.com/album/32230540","retrieved":1730172125117},{"title":"Over Each Other (네이버 바이브 ─ 최신앨범 ─ 해외)","contents":"Linkin Park","link":"https://vibe.naver.com/album/32234535","retrieved":1730085906133},{"title":"Duets (30th Anniversary) (네이버 바이브 ─ 최신앨범 ─ 해외)","contents":"Andrea Bocelli","link":"https://vibe.naver.com/album/32230857","retrieved":1730085906143},{"title":"Mom's Old Car (네이버 바이브 ─ 최신앨범 ─ 해외)","contents":"Walk Off The Earth","link":"https://vibe.naver.com/album/32228920","retrieved":1730085906143},{"title":"WHY ALWAYS ME? (네이버 바이브 ─ 최신앨범 ─ 해외)","contents":"Cochise","link":"https://vibe.naver.com/album/32232686","retrieved":1730085906143},{"title":"Dystopia (네이버 바이브 ─ 최신앨범 ─ 해외)","contents":"ONE OK ROCK","link":"https://vibe.naver.com/album/32232144","retrieved":1730085906143},{"title":"Swallow My Tears (네이버 바이브 ─ 최신앨범 ─ 해외)","contents":"Gwen Stefani","link":"https://vibe.naver.com/album/32230815","retrieved":1730085906143},{"title":"I Wanna Dance With Somebody (네이버 바이브 ─ 최신앨범 ─ 해외)","contents":"Blossoms","link":"https://vibe.naver.com/album/32229668","retrieved":1730085906145},{"title":"Water Sign (feat. Aluna) (네이버 바이브 ─ 최신앨범 ─ 해외)","contents":"Jai Wolf","link":"https://vibe.naver.com/album/32225719","retrieved":1730085906145},{"title":"Begin Again (네이버 바이브 ─ 최신앨범 ─ 해외)","contents":"Maya Delilah","link":"https://vibe.naver.com/album/32230789","retrieved":1730085906145},{"title":"Be Alright (네이버 바이브 ─ 최신앨범 ─ 해외)","contents":"Joel Corry","link":"https://vibe.naver.com/album/32232152","retrieved":1730085906145},{"title":"pony up! (네이버 바이브 ─ 최신앨범 ─ 해외)","contents":"Hadji Gaviota","link":"https://vibe.naver.com/album/32236103","retrieved":1730085906145},{"title":"Touch Me (네이버 바이브 ─ 최신앨범 ─ 해외)","contents":"ILYAA","link":"https://vibe.naver.com/album/32236160","retrieved":1730085906145},{"title":"Where We Go (Calypso) (Soft Analog Version) (네이버 바이브 ─ 최신앨범 ─ 해외)","contents":"Compact Disk Dummies","link":"https://vibe.naver.com/album/32238641","retrieved":1730085906145},{"title":"Kiss To Forget (네이버 바이브 ─ 최신앨범 ─ 해외)","contents":"Brett Young","link":"https://vibe.naver.com/album/32230649","retrieved":1730085906145},{"title":"I Hate You (You Hate Me) (네이버 바이브 ─ 최신앨범 ─ 해외)","contents":"DWLLRS","link":"https://vibe.naver.com/album/32230779","retrieved":1730085906145},{"title":"MEGAN: ACT II (네이버 바이브 ─ 최신앨범 ─ 해외)","contents":"Megan Thee Stallion","link":"https://vibe.naver.com/album/32235932","retrieved":1729829984931},{"title":"Disease (네이버 바이브 ─ 최신앨범 ─ 해외)","contents":"Lady Gaga","link":"https://vibe.naver.com/album/32235999","retrieved":1729847764598},{"title":"GOLD (English Ver.) (네이버 바이브 ─ 최신앨범 ─ 해외)","contents":"ITZY(있지)","link":"https://vibe.naver.com/album/32232238","retrieved":1729829984931},{"title":"The Great Impersonator (네이버 바이브 ─ 최신앨범 ─ 해외)","contents":"Halsey","link":"https://vibe.naver.com/album/32232651","retrieved":1729826525830},{"title":"Passenger Princess / Adam (네이버 바이브 ─ 최신앨범 ─ 해외)","contents":"Aminé","link":"https://vibe.naver.com/album/32223790","retrieved":1729826525833},{"title":"Arachnids (네이버 바이브 ─ 최신앨범 ─ 해외)","contents":"Disclosure","link":"https://vibe.naver.com/album/32225709","retrieved":1729826525833},{"title":"Best Friends (네이버 바이브 ─ 최신앨범 ─ 해외)","contents":"Jesse Barrera","link":"https://vibe.naver.com/album/32232208","retrieved":1729826525833},{"title":"Sweeter (네이버 바이브 ─ 최신앨범 ─ 해외)","contents":"Masked Wolf","link":"https://vibe.naver.com/album/32232643","retrieved":1729826525833},{"title":"We Have All The Time In The World (Cam Blackwood & Swindle Version) (네이버 바이브 ─ 최신앨범 ─ 해외)","contents":"Gregory Porter","link":"https://vibe.naver.com/album/32230423","retrieved":1729826525833},{"title":"Have Yourself a Merry Little Christmas (네이버 바이브 ─ 최신앨범 ─ 해외)","contents":"Walker Hayes","link":"https://vibe.naver.com/album/32232722","retrieved":1729826525834},{"title":"Will You Love Me When I'm Dead (네이버 바이브 ─ 최신앨범 ─ 해외)","contents":"Amira Elfeky","link":"https://vibe.naver.com/album/32225901","retrieved":1729826525834},{"title":"U and I (Intertwine) (네이버 바이브 ─ 최신앨범 ─ 해외)","contents":"Nicky Youre","link":"https://vibe.naver.com/album/32225712","retrieved":1729826525836},{"title":"“&” (Ampersand) (네이버 바이브 ─ 최신앨범 ─ 해외)","contents":"Bastille","link":"https://vibe.naver.com/album/32230748","retrieved":1729826525838},{"title":"The Spark (Felix Jaehn Remix) (네이버 바이브 ─ 최신앨범 ─ 해외)","contents":"Kabin Crew","link":"https://vibe.naver.com/album/32232629","retrieved":1729826525840},{"title":"No Children (네이버 바이브 ─ 최신앨범 ─ 해외)","contents":"Jack Kays","link":"https://vibe.naver.com/album/32232687","retrieved":1729826525842},{"title":"hold my hand (네이버 바이브 ─ 최신앨범 ─ 해외)","contents":"Knock2","link":"https://vibe.naver.com/album/32231092","retrieved":1729826525844},{"title":"Avalanches (DARGZ Remix) (네이버 바이브 ─ 최신앨범 ─ 해외)","contents":"Caravan Palace","link":"https://vibe.naver.com/album/32232306","retrieved":1729826525846},{"title":"Superstar (네이버 바이브 ─ 최신앨범 ─ 해외)","contents":"KEN MIYAKE","link":"https://vibe.naver.com/album/32235730","retrieved":1729826525848},{"title":"Feeling OK? (네이버 바이브 ─ 최신앨범 ─ 해외)","contents":"babychair","link":"https://vibe.naver.com/album/32232155","retrieved":1729826525850},{"title":"SHOOT MY SHOT (네이버 바이브 ─ 최신앨범 ─ 해외)","contents":"Nieman","link":"https://vibe.naver.com/album/32232502","retrieved":1729826525852},{"title":"Trust (네이버 바이브 ─ 최신앨범 ─ 해외)","contents":"Chris Crone","link":"https://vibe.naver.com/album/32232380","retrieved":1729826525864},{"title":"Elijah Would! (네이버 바이브 ─ 최신앨범 ─ 해외)","contents":"Elijah Woods","link":"https://vibe.naver.com/album/32235794","retrieved":1729826525866},{"title":"CLICHÉ (네이버 바이브 ─ 최신앨범 ─ 모든 앨범)","contents":"<!----><a data-v-78809b3d=\"\" href=\"/album/32239229\" class=\"title\"><span data-v-78809b3d=\"\" class=\"text_wrap\"><span data-v-78809b3d=\"\" id=\"32239229\" class=\"text\">CLICHÉ</span><!----><!----></span><span data-v-78809b3d=\"\" class=\"blind\">페이지로 이동</span></a><div data-v-78809b3d=\"\" class=\"artist\"><span data-v-78809b3d=\"\" class=\"artist_sub_inner\"><span><a href=\"/artist/329023\" class=\"link_artist\"><span class=\"text\">적재</span></a><!----></span></span><span data-v-78809b3d=\"\" class=\"blind\">아티스트명</span></div>","link":"https://vibe.naver.com/album/32239229","retrieved":1730193352629},{"title":"finstagram (네이버 바이브 ─ 최신앨범 ─ 모든 앨범)","contents":"<!----><a data-v-78809b3d=\"\" href=\"/album/32238804\" class=\"title\"><span data-v-78809b3d=\"\" class=\"text_wrap\"><span data-v-78809b3d=\"\" id=\"32238804\" class=\"text\">finstagram</span><!----><!----></span><span data-v-78809b3d=\"\" class=\"blind\">페이지로 이동</span></a><div data-v-78809b3d=\"\" class=\"artist\"><span data-v-78809b3d=\"\" class=\"artist_sub_inner\"><span><a href=\"/artist/1466571\" class=\"link_artist\"><span class=\"text\">OLNL (오르내림)</span></a><!----></span></span><span data-v-78809b3d=\"\" class=\"blind\">아티스트명</span></div>","link":"https://vibe.naver.com/album/32238804","retrieved":1730193352629},{"title":"스테이지 파이터(STF) Original Vol.4 (네이버 바이브 ─ 최신앨범 ─ 모든 앨범)","contents":"<!----><a data-v-78809b3d=\"\" href=\"/album/32239106\" class=\"title\"><span data-v-78809b3d=\"\" class=\"text_wrap\"><span data-v-78809b3d=\"\" id=\"32239106\" class=\"text\">스테이지 파이터(STF) Original Vol.4</span><!----><!----></span><span data-v-78809b3d=\"\" class=\"blind\">페이지로 이동</span></a><div data-v-78809b3d=\"\" class=\"artist\"><span data-v-78809b3d=\"\" class=\"artist_sub_inner\"><span><span class=\"link_artist\">Various Artists</span><!----></span></span><span data-v-78809b3d=\"\" class=\"blind\">아티스트명</span></div>","link":"https://vibe.naver.com/album/32239106","retrieved":1730193352620},{"title":"내 마음을 뺏는 건 (네이버 바이브 ─ 최신앨범 ─ 모든 앨범)","contents":"<!----><a data-v-78809b3d=\"\" href=\"/album/32239094\" class=\"title\"><span data-v-78809b3d=\"\" class=\"text_wrap\"><span data-v-78809b3d=\"\" id=\"32239094\" class=\"text\">내 마음을 뺏는 건</span><!----><!----></span><span data-v-78809b3d=\"\" class=\"blind\">페이지로 이동</span></a><div data-v-78809b3d=\"\" class=\"artist\"><span data-v-78809b3d=\"\" class=\"artist_sub_inner\"><span><a href=\"/artist/259939\" class=\"link_artist\"><span class=\"text\">송하예</span></a><!----></span></span><span data-v-78809b3d=\"\" class=\"blind\">아티스트명</span></div>","link":"https://vibe.naver.com/album/32239094","retrieved":1730193352640},{"title":"솔라감성 Part 8 (네이버 바이브 ─ 최신앨범 ─ 모든 앨범)","contents":"<!----><a data-v-78809b3d=\"\" href=\"/album/32239170\" class=\"title\"><span data-v-78809b3d=\"\" class=\"text_wrap\"><span data-v-78809b3d=\"\" id=\"32239170\" class=\"text\">솔라감성 Part 8</span><!----><!----></span><span data-v-78809b3d=\"\" class=\"blind\">페이지로 이동</span></a><div data-v-78809b3d=\"\" class=\"artist\"><span data-v-78809b3d=\"\" class=\"artist_sub_inner\"><span><a href=\"/artist/313698\" class=\"link_artist\"><span class=\"text\">솔라(마마무)</span></a><!----></span></span><span data-v-78809b3d=\"\" class=\"blind\">아티스트명</span></div>","link":"https://vibe.naver.com/album/32239170","retrieved":1730193352642},{"title":"ONE (네이버 바이브 ─ 최신앨범 ─ 모든 앨범)","contents":"<!----><a data-v-78809b3d=\"\" href=\"/album/32238886\" class=\"title\"><span data-v-78809b3d=\"\" class=\"text_wrap\"><span data-v-78809b3d=\"\" id=\"32238886\" class=\"text\">ONE</span><!----><!----></span><span data-v-78809b3d=\"\" class=\"blind\">페이지로 이동</span></a><div data-v-78809b3d=\"\" class=\"artist\"><span data-v-78809b3d=\"\" class=\"artist_sub_inner\"><span><a href=\"/artist/2396211\" class=\"link_artist\"><span class=\"text\">blah</span></a><!----></span></span><span data-v-78809b3d=\"\" class=\"blind\">아티스트명</span></div>","link":"https://vibe.naver.com/album/32238886","retrieved":1730193352642},{"title":"Branding (네이버 바이브 ─ 최신앨범 ─ 모든 앨범)","contents":"<!----><a data-v-78809b3d=\"\" href=\"/album/32240597\" class=\"title\"><span data-v-78809b3d=\"\" class=\"text_wrap\"><span data-v-78809b3d=\"\" id=\"32240597\" class=\"text\">Branding</span><!----><!----></span><span data-v-78809b3d=\"\" class=\"blind\">페이지로 이동</span></a><div data-v-78809b3d=\"\" class=\"artist\"><span data-v-78809b3d=\"\" class=\"artist_sub_inner\"><span><a href=\"/artist/14007\" class=\"link_artist\"><span class=\"text\">스케리피(Scary'P)</span></a><!----></span></span><span data-v-78809b3d=\"\" class=\"blind\">아티스트명</span></div>","link":"https://vibe.naver.com/album/32240597","retrieved":1730193352642},{"title":"나침반 (네이버 바이브 ─ 최신앨범 ─ 모든 앨범)","contents":"<!----><a data-v-78809b3d=\"\" href=\"/album/32238818\" class=\"title\"><span data-v-78809b3d=\"\" class=\"text_wrap\"><span data-v-78809b3d=\"\" id=\"32238818\" class=\"text\">나침반</span><!----><!----></span><span data-v-78809b3d=\"\" class=\"blind\">페이지로 이동</span></a><div data-v-78809b3d=\"\" class=\"artist\"><span data-v-78809b3d=\"\" class=\"artist_sub_inner\"><span><a href=\"/artist/5351390\" class=\"link_artist\"><span class=\"text\">한로로</span></a><!----></span></span><span data-v-78809b3d=\"\" class=\"blind\">아티스트명</span></div>","link":"https://vibe.naver.com/album/32238818","retrieved":1730193352642},{"title":"있어주라 (네이버 바이브 ─ 최신앨범 ─ 모든 앨범)","contents":"<!----><a data-v-78809b3d=\"\" href=\"/album/32238825\" class=\"title\"><span data-v-78809b3d=\"\" class=\"text_wrap\"><span data-v-78809b3d=\"\" id=\"32238825\" class=\"text\">있어주라</span><!----><!----></span><span data-v-78809b3d=\"\" class=\"blind\">페이지로 이동</span></a><div data-v-78809b3d=\"\" class=\"artist\"><span data-v-78809b3d=\"\" class=\"artist_sub_inner\"><span><a href=\"/artist/3820857\" class=\"link_artist\"><span class=\"text\">권지은</span></a><!----></span></span><span data-v-78809b3d=\"\" class=\"blind\">아티스트명</span></div>","link":"https://vibe.naver.com/album/32238825","retrieved":1730193352642},{"title":"What Is Your Phone Number (네이버 바이브 ─ 최신앨범 ─ 모든 앨범)","contents":"<!----><a data-v-78809b3d=\"\" href=\"/album/32239102\" class=\"title\"><span data-v-78809b3d=\"\" class=\"text_wrap\"><span data-v-78809b3d=\"\" id=\"32239102\" class=\"text\">What Is Your Phone Number</span><!----><!----></span><span data-v-78809b3d=\"\" class=\"blind\">페이지로 이동</span></a><div data-v-78809b3d=\"\" class=\"artist\"><span data-v-78809b3d=\"\" class=\"artist_sub_inner\"><span><a href=\"/artist/2895703\" class=\"link_artist\"><span class=\"text\">oid(오이드)</span></a><!----></span></span><span data-v-78809b3d=\"\" class=\"blind\">아티스트명</span></div>","link":"https://vibe.naver.com/album/32239102","retrieved":1730193352642},{"title":"THE BOYZ 9th MINI ALBUM [導火線] (네이버 바이브 ─ 최신앨범 ─ 모든 앨범)","contents":"<!----><a data-v-78809b3d=\"\" href=\"/album/32238726\" class=\"title\"><span data-v-78809b3d=\"\" class=\"text_wrap\"><span data-v-78809b3d=\"\" id=\"32238726\" class=\"text\">THE BOYZ 9th MINI ALBUM [導火線]</span><!----><!----></span><span data-v-78809b3d=\"\" class=\"blind\">페이지로 이동</span></a><div data-v-78809b3d=\"\" class=\"artist\"><span data-v-78809b3d=\"\" class=\"artist_sub_inner\"><span><a href=\"/artist/2138891\" class=\"link_artist\"><span class=\"text\">더보이즈(THE BOYZ)</span></a><!----></span></span><span data-v-78809b3d=\"\" class=\"blind\">아티스트명</span></div>","link":"https://vibe.naver.com/album/32238726","retrieved":1730106994898},{"title":"LOVEE (네이버 바이브 ─ 최신앨범 ─ 모든 앨범)","contents":"<!----><a data-v-78809b3d=\"\" href=\"/album/32238822\" class=\"title\"><span data-v-78809b3d=\"\" class=\"text_wrap\"><span data-v-78809b3d=\"\" id=\"32238822\" class=\"text\">LOVEE</span><!----><!----></span><span data-v-78809b3d=\"\" class=\"blind\">페이지로 이동</span></a><div data-v-78809b3d=\"\" class=\"artist\"><span data-v-78809b3d=\"\" class=\"artist_sub_inner\"><span><a href=\"/artist/546664\" class=\"link_artist\"><span class=\"text\">Wynn(윈)</span></a><!----></span></span><span data-v-78809b3d=\"\" class=\"blind\">아티스트명</span></div>","link":"https://vibe.naver.com/album/32238822","retrieved":1730172117788},{"title":"변하지 않을 멜로디 (Feat. JAEHA) (네이버 바이브 ─ 최신앨범 ─ 모든 앨범)","contents":"<!----><a data-v-78809b3d=\"\" href=\"/album/32239122\" class=\"title\"><span data-v-78809b3d=\"\" class=\"text_wrap\"><span data-v-78809b3d=\"\" id=\"32239122\" class=\"text\">변하지 않을 멜로디 (Feat. JAEHA)</span><!----><!----></span><span data-v-78809b3d=\"\" class=\"blind\">페이지로 이동</span></a><div data-v-78809b3d=\"\" class=\"artist\"><span data-v-78809b3d=\"\" class=\"artist_sub_inner\"><span><a href=\"/artist/4456338\" class=\"link_artist\"><span class=\"text\">Youngcode</span></a><!----></span></span><span data-v-78809b3d=\"\" class=\"blind\">아티스트명</span></div>","link":"https://vibe.naver.com/album/32239122","retrieved":1730172117788},{"title":"San Diego Blues (네이버 바이브 ─ 최신앨범 ─ 모든 앨범)","contents":"<!----><a data-v-78809b3d=\"\" href=\"/album/32239099\" class=\"title\"><span data-v-78809b3d=\"\" class=\"text_wrap\"><span data-v-78809b3d=\"\" id=\"32239099\" class=\"text\">San Diego Blues</span><!----><!----></span><span data-v-78809b3d=\"\" class=\"blind\">페이지로 이동</span></a><div data-v-78809b3d=\"\" class=\"artist\"><span data-v-78809b3d=\"\" class=\"artist_sub_inner\"><span><a href=\"/artist/2407629\" class=\"link_artist\"><span class=\"text\">Austn(오스틴)</span></a><!----></span></span><span data-v-78809b3d=\"\" class=\"blind\">아티스트명</span></div>","link":"https://vibe.naver.com/album/32239099","retrieved":1730172117788},{"title":"컬러링 '야야야' (원곡 베이비복스) (네이버 바이브 ─ 최신앨범 ─ 모든 앨범)","contents":"<!----><a data-v-78809b3d=\"\" href=\"/album/32239090\" class=\"title\"><span data-v-78809b3d=\"\" class=\"text_wrap\"><span data-v-78809b3d=\"\" id=\"32239090\" class=\"text\">컬러링 '야야야' (원곡 베이비복스)</span><!----><!----></span><span data-v-78809b3d=\"\" class=\"blind\">페이지로 이동</span></a><div data-v-78809b3d=\"\" class=\"artist\"><span data-v-78809b3d=\"\" class=\"artist_sub_inner\"><span><a href=\"/artist/2224902\" class=\"link_artist\"><span class=\"text\">D2ear</span></a><!----></span></span><span data-v-78809b3d=\"\" class=\"blind\">아티스트명</span></div>","link":"https://vibe.naver.com/album/32239090","retrieved":1730172117788},{"title":"Heart Of A Woman (네이버 바이브 ─ 최신앨범 ─ 모든 앨범)","contents":"<!----><a data-v-78809b3d=\"\" href=\"/album/32232047\" class=\"title\"><span data-v-78809b3d=\"\" class=\"text_wrap\"><span data-v-78809b3d=\"\" id=\"32232047\" class=\"text\">Heart Of A Woman</span><!----><!----></span><span data-v-78809b3d=\"\" class=\"blind\">페이지로 이동</span></a><div data-v-78809b3d=\"\" class=\"artist\"><span data-v-78809b3d=\"\" class=\"artist_sub_inner\"><span><a href=\"/artist/2410131\" class=\"link_artist\"><span class=\"text\">Summer Walker</span></a><!----></span></span><span data-v-78809b3d=\"\" class=\"blind\">아티스트명</span></div>","link":"https://vibe.naver.com/album/32232047","retrieved":1730172125111},{"title":"Magpie (네이버 바이브 ─ 최신앨범 ─ 모든 앨범)","contents":"<!----><a data-v-78809b3d=\"\" href=\"/album/32232655\" class=\"title\"><span data-v-78809b3d=\"\" class=\"text_wrap\"><span data-v-78809b3d=\"\" id=\"32232655\" class=\"text\">Magpie</span><!----><!----></span><span data-v-78809b3d=\"\" class=\"blind\">페이지로 이동</span></a><div data-v-78809b3d=\"\" class=\"artist\"><span data-v-78809b3d=\"\" class=\"artist_sub_inner\"><span><a href=\"/artist/2083214\" class=\"link_artist\"><span class=\"text\">Peach pit</span></a><!----></span></span><span data-v-78809b3d=\"\" class=\"blind\">아티스트명</span></div>","link":"https://vibe.naver.com/album/32232655","retrieved":1730172125111},{"title":"Loveland (네이버 바이브 ─ 최신앨범 ─ 모든 앨범)","contents":"<!----><a data-v-78809b3d=\"\" href=\"/album/32231976\" class=\"title\"><span data-v-78809b3d=\"\" class=\"text_wrap\"><span data-v-78809b3d=\"\" id=\"32231976\" class=\"text\">Loveland</span><!----><!----></span><span data-v-78809b3d=\"\" class=\"blind\">페이지로 이동</span></a><div data-v-78809b3d=\"\" class=\"artist\"><span data-v-78809b3d=\"\" class=\"artist_sub_inner\"><span><a href=\"/artist/3687414\" class=\"link_artist\"><span class=\"text\">Fly By Midnight</span></a><!----></span></span><span data-v-78809b3d=\"\" class=\"blind\">아티스트명</span></div>","link":"https://vibe.naver.com/album/32231976","retrieved":1730172125113},{"title":"wasn't a fighting kid (네이버 바이브 ─ 최신앨범 ─ 모든 앨범)","contents":"<!----><a data-v-78809b3d=\"\" href=\"/album/32232151\" class=\"title\"><span data-v-78809b3d=\"\" class=\"text_wrap\"><span data-v-78809b3d=\"\" id=\"32232151\" class=\"text\">wasn't a fighting kid</span><!----><!----></span><span data-v-78809b3d=\"\" class=\"blind\">페이지로 이동</span></a><div data-v-78809b3d=\"\" class=\"artist\"><span data-v-78809b3d=\"\" class=\"artist_sub_inner\"><span><a href=\"/artist/3661114\" class=\"link_artist\"><span class=\"text\">Thomas Headon</span></a><!----></span></span><span data-v-78809b3d=\"\" class=\"blind\">아티스트명</span></div>","link":"https://vibe.naver.com/album/32232151","retrieved":1730172125113},{"title":"눈에 보이지 않는 노래는 (네이버 바이브 ─ 최신앨범 ─ 모든 앨범)","contents":"<!----><a data-v-78809b3d=\"\" href=\"/album/32239168\" class=\"title\"><span data-v-78809b3d=\"\" class=\"text_wrap\"><span data-v-78809b3d=\"\" id=\"32239168\" class=\"text\">눈에 보이지 않는 노래는</span><!----><!----></span><span data-v-78809b3d=\"\" class=\"blind\">페이지로 이동</span></a><div data-v-78809b3d=\"\" class=\"artist\"><span data-v-78809b3d=\"\" class=\"artist_sub_inner\"><span><a href=\"/artist/5874642\" class=\"link_artist\"><span class=\"text\">연정(YEONJEONG)</span></a><!----></span></span><span data-v-78809b3d=\"\" class=\"blind\">아티스트명</span></div>","link":"https://vibe.naver.com/album/32239168","retrieved":1730172117800},{"title":"사랑이라 말했던 너의 모든 순간들이 (네이버 바이브 ─ 최신앨범 ─ 모든 앨범)","contents":"<!----><a data-v-78809b3d=\"\" href=\"/album/32239566\" class=\"title\"><span data-v-78809b3d=\"\" class=\"text_wrap\"><span data-v-78809b3d=\"\" id=\"32239566\" class=\"text\">사랑이라 말했던 너의 모든 순간들이</span><!----><!----></span><span data-v-78809b3d=\"\" class=\"blind\">페이지로 이동</span></a><div data-v-78809b3d=\"\" class=\"artist\"><span data-v-78809b3d=\"\" class=\"artist_sub_inner\"><span><a href=\"/artist/8386802\" class=\"link_artist\"><span class=\"text\">양하진</span></a><!----></span></span><span data-v-78809b3d=\"\" class=\"blind\">아티스트명</span></div>","link":"https://vibe.naver.com/album/32239566","retrieved":1730172117800},{"title":"ONCE AGAIN (네이버 바이브 ─ 최신앨범 ─ 모든 앨범)","contents":"<!----><a data-v-78809b3d=\"\" href=\"/album/32238955\" class=\"title\"><span data-v-78809b3d=\"\" class=\"text_wrap\"><span data-v-78809b3d=\"\" id=\"32238955\" class=\"text\">ONCE AGAIN</span><!----><!----></span><span data-v-78809b3d=\"\" class=\"blind\">페이지로 이동</span></a><div data-v-78809b3d=\"\" class=\"artist\"><span data-v-78809b3d=\"\" class=\"artist_sub_inner\"><span><a href=\"/artist/10736\" class=\"link_artist\"><span class=\"text\">이재원</span></a><!----></span></span><span data-v-78809b3d=\"\" class=\"blind\">아티스트명</span></div>","link":"https://vibe.naver.com/album/32238955","retrieved":1730172117800},{"title":"Luv tape (네이버 바이브 ─ 최신앨범 ─ 모든 앨범)","contents":"<!----><a data-v-78809b3d=\"\" href=\"/album/32239140\" class=\"title\"><span data-v-78809b3d=\"\" class=\"text_wrap\"><span data-v-78809b3d=\"\" id=\"32239140\" class=\"text\">Luv tape</span><!----><!----></span><span data-v-78809b3d=\"\" class=\"blind\">페이지로 이동</span></a><div data-v-78809b3d=\"\" class=\"artist\"><span data-v-78809b3d=\"\" class=\"artist_sub_inner\"><span><a href=\"/artist/2684270\" class=\"link_artist\"><span class=\"text\">리플리(RIPLEY)</span></a><!----></span></span><span data-v-78809b3d=\"\" class=\"blind\">아티스트명</span></div>","link":"https://vibe.naver.com/album/32239140","retrieved":1730172117800},{"title":"Dream of You (Korean Ver.) (네이버 바이브 ─ 최신앨범 ─ 모든 앨범)","contents":"<!----><a data-v-78809b3d=\"\" href=\"/album/32238869\" class=\"title\"><span data-v-78809b3d=\"\" class=\"text_wrap\"><span data-v-78809b3d=\"\" id=\"32238869\" class=\"text\">Dream of You (Korean Ver.)</span><!----><!----></span><span data-v-78809b3d=\"\" class=\"blind\">페이지로 이동</span></a><div data-v-78809b3d=\"\" class=\"artist\"><span data-v-78809b3d=\"\" class=\"artist_sub_inner\"><span><a href=\"/artist/1867628\" class=\"link_artist\"><span class=\"text\">SCOOL</span></a><!----></span></span><span data-v-78809b3d=\"\" class=\"blind\">아티스트명</span></div>","link":"https://vibe.naver.com/album/32238869","retrieved":1730172117800},{"title":"꽃샘추위 주의보 (네이버 바이브 ─ 최신앨범 ─ 모든 앨범)","contents":"<!----><a data-v-78809b3d=\"\" href=\"/album/32239022\" class=\"title\"><span data-v-78809b3d=\"\" class=\"text_wrap\"><span data-v-78809b3d=\"\" id=\"32239022\" class=\"text\">꽃샘추위 주의보</span><!----><!----></span><span data-v-78809b3d=\"\" class=\"blind\">페이지로 이동</span></a><div data-v-78809b3d=\"\" class=\"artist\"><span data-v-78809b3d=\"\" class=\"artist_sub_inner\"><span><a href=\"/artist/5417902\" class=\"link_artist\"><span class=\"text\">이을 (E.ul)</span></a><!----></span></span><span data-v-78809b3d=\"\" class=\"blind\">아티스트명</span></div>","link":"https://vibe.naver.com/album/32239022","retrieved":1730172117800},{"title":"Symphony of Lungs - BBC Proms at the Royal Albert Hall (네이버 바이브 ─ 최신앨범 ─ 모든 앨범)","contents":"<!----><a data-v-78809b3d=\"\" href=\"/album/32230746\" class=\"title\"><span data-v-78809b3d=\"\" class=\"text_wrap\"><span data-v-78809b3d=\"\" id=\"32230746\" class=\"text\">Symphony of Lungs - BBC Proms at the Royal Albert Hall</span><!----><!----></span><span data-v-78809b3d=\"\" class=\"blind\">페이지로 이동</span></a><div data-v-78809b3d=\"\" class=\"artist\"><span data-v-78809b3d=\"\" class=\"artist_sub_inner\"><span><a href=\"/artist/120381\" class=\"link_artist\"><span class=\"text\">Florence + The Machine</span></a><span>, </span></span><span><a href=\"/artist/441053\" class=\"link_artist\"><span class=\"text\">Jules Buckley</span></a><!----></span></span><span data-v-78809b3d=\"\" class=\"blind\">아티스트명</span></div>","link":"https://vibe.naver.com/album/32230746","retrieved":1730172125113},{"title":"YOUR WAY'S BETTER (네이버 바이브 ─ 최신앨범 ─ 모든 앨범)","contents":"<!----><a data-v-78809b3d=\"\" href=\"/album/32235893\" class=\"title\"><span data-v-78809b3d=\"\" class=\"text_wrap\"><span data-v-78809b3d=\"\" id=\"32235893\" class=\"text\">YOUR WAY'S BETTER</span><!----><!----></span><span data-v-78809b3d=\"\" class=\"blind\">페이지로 이동</span></a><div data-v-78809b3d=\"\" class=\"artist\"><span data-v-78809b3d=\"\" class=\"artist_sub_inner\"><span><a href=\"/artist/2899526\" class=\"link_artist\"><span class=\"text\">Forrest Frank</span></a><!----></span></span><span data-v-78809b3d=\"\" class=\"blind\">아티스트명</span></div>","link":"https://vibe.naver.com/album/32235893","retrieved":1730172125113},{"title":"Two Shades Blonder (네이버 바이브 ─ 최신앨범 ─ 모든 앨범)","contents":"<!----><a data-v-78809b3d=\"\" href=\"/album/32232691\" class=\"title\"><span data-v-78809b3d=\"\" class=\"text_wrap\"><span data-v-78809b3d=\"\" id=\"32232691\" class=\"text\">Two Shades Blonder</span><!----><!----></span><span data-v-78809b3d=\"\" class=\"blind\">페이지로 이동</span></a><div data-v-78809b3d=\"\" class=\"artist\"><span data-v-78809b3d=\"\" class=\"artist_sub_inner\"><span><a href=\"/artist/5437220\" class=\"link_artist\"><span class=\"text\">Devon Cole</span></a><!----></span></span><span data-v-78809b3d=\"\" class=\"blind\">아티스트명</span></div>","link":"https://vibe.naver.com/album/32232691","retrieved":1730172125113},{"title":"No Pressure (네이버 바이브 ─ 최신앨범 ─ 모든 앨범)","contents":"<!----><a data-v-78809b3d=\"\" href=\"/album/32238123\" class=\"title\"><span data-v-78809b3d=\"\" class=\"text_wrap\"><span data-v-78809b3d=\"\" id=\"32238123\" class=\"text\">No Pressure</span><!----><!----></span><span data-v-78809b3d=\"\" class=\"blind\">페이지로 이동</span></a><div data-v-78809b3d=\"\" class=\"artist\"><span data-v-78809b3d=\"\" class=\"artist_sub_inner\"><span><a href=\"/artist/3185123\" class=\"link_artist\"><span class=\"text\">KnowKnow</span></a><!----></span></span><span data-v-78809b3d=\"\" class=\"blind\">아티스트명</span></div>","link":"https://vibe.naver.com/album/32238123","retrieved":1730172125113},{"title":"A Christmas Album (네이버 바이브 ─ 최신앨범 ─ 모든 앨범)","contents":"<!----><a data-v-78809b3d=\"\" href=\"/album/32232045\" class=\"title\"><span data-v-78809b3d=\"\" class=\"text_wrap\"><span data-v-78809b3d=\"\" id=\"32232045\" class=\"text\">A Christmas Album</span><!----><!----></span><span data-v-78809b3d=\"\" class=\"blind\">페이지로 이동</span></a><div data-v-78809b3d=\"\" class=\"artist\"><span data-v-78809b3d=\"\" class=\"artist_sub_inner\"><span><a href=\"/artist/4794731\" class=\"link_artist\"><span class=\"text\">Matthew Ifield</span></a><!----></span></span><span data-v-78809b3d=\"\" class=\"blind\">아티스트명</span></div>","link":"https://vibe.naver.com/album/32232045","retrieved":1730172125113},{"title":"746 - The 1st Album (네이버 바이브 ─ 최신앨범 ─ 모든 앨범)","contents":"<!----><a data-v-78809b3d=\"\" href=\"/album/32121906\" class=\"title\"><span data-v-78809b3d=\"\" class=\"text_wrap\"><span data-v-78809b3d=\"\" id=\"32121906\" class=\"text\">746 - The 1st Album</span><span data-v-78809b3d=\"\" class=\"badge_dolby\"><span data-v-78809b3d=\"\" class=\"blind\">Dolby Atmos 지원</span></span><!----></span><span data-v-78809b3d=\"\" class=\"blind\">페이지로 이동</span></a><div data-v-78809b3d=\"\" class=\"artist\"><span data-v-78809b3d=\"\" class=\"artist_sub_inner\"><span><a href=\"/artist/2900003\" class=\"link_artist\"><span class=\"text\">최유리</span></a><!----></span></span><span data-v-78809b3d=\"\" class=\"blind\">아티스트명</span></div>","link":"https://vibe.naver.com/album/32121906","retrieved":1730106994898},{"title":"Passion Of Various Types (네이버 바이브 ─ 최신앨범 ─ 모든 앨범)","contents":"<!----><a data-v-78809b3d=\"\" href=\"/album/32238602\" class=\"title\"><span data-v-78809b3d=\"\" class=\"text_wrap\"><span data-v-78809b3d=\"\" id=\"32238602\" class=\"text\">Passion Of Various Types</span><!----><!----></span><span data-v-78809b3d=\"\" class=\"blind\">페이지로 이동</span></a><div data-v-78809b3d=\"\" class=\"artist\"><span data-v-78809b3d=\"\" class=\"artist_sub_inner\"><span><a href=\"/artist/3574483\" class=\"link_artist\"><span class=\"text\">Low Hanging Fruits</span></a><!----></span></span><span data-v-78809b3d=\"\" class=\"blind\">아티스트명</span></div>","link":"https://vibe.naver.com/album/32238602","retrieved":1730106994898},{"title":"그냥 사랑이 식었다고 말하지 그랬어 (네이버 바이브 ─ 최신앨범 ─ 모든 앨범)","contents":"<!----><a data-v-78809b3d=\"\" href=\"/album/32236174\" class=\"title\"><span data-v-78809b3d=\"\" class=\"text_wrap\"><span data-v-78809b3d=\"\" id=\"32236174\" class=\"text\">그냥 사랑이 식었다고 말하지 그랬어</span><!----><!----></span><span data-v-78809b3d=\"\" class=\"blind\">페이지로 이동</span></a><div data-v-78809b3d=\"\" class=\"artist\"><span data-v-78809b3d=\"\" class=\"artist_sub_inner\"><span><a href=\"/artist/211475\" class=\"link_artist\"><span class=\"text\">이소정</span></a><!----></span></span><span data-v-78809b3d=\"\" class=\"blind\">아티스트명</span></div>","link":"https://vibe.naver.com/album/32236174","retrieved":1730106994898},{"title":"SHINE (네이버 바이브 ─ 최신앨범 ─ 모든 앨범)","contents":"<!----><a data-v-78809b3d=\"\" href=\"/album/32238855\" class=\"title\"><span data-v-78809b3d=\"\" class=\"text_wrap\"><span data-v-78809b3d=\"\" id=\"32238855\" class=\"text\">SHINE</span><!----><!----></span><span data-v-78809b3d=\"\" class=\"blind\">페이지로 이동</span></a><div data-v-78809b3d=\"\" class=\"artist\"><span data-v-78809b3d=\"\" class=\"artist_sub_inner\"><span><a href=\"/artist/490053\" class=\"link_artist\"><span class=\"text\">손태진</span></a><!----></span></span><span data-v-78809b3d=\"\" class=\"blind\">아티스트명</span></div>","link":"https://vibe.naver.com/album/32238855","retrieved":1730106994899},{"title":"마치 사랑처럼 (네이버 바이브 ─ 최신앨범 ─ 모든 앨범)","contents":"<!----><a data-v-78809b3d=\"\" href=\"/album/32238280\" class=\"title\"><span data-v-78809b3d=\"\" class=\"text_wrap\"><span data-v-78809b3d=\"\" id=\"32238280\" class=\"text\">마치 사랑처럼</span><!----><!----></span><span data-v-78809b3d=\"\" class=\"blind\">페이지로 이동</span></a><div data-v-78809b3d=\"\" class=\"artist\"><span data-v-78809b3d=\"\" class=\"artist_sub_inner\"><span><a href=\"/artist/5881345\" class=\"link_artist\"><span class=\"text\">자정</span></a><!----></span></span><span data-v-78809b3d=\"\" class=\"blind\">아티스트명</span></div>","link":"https://vibe.naver.com/album/32238280","retrieved":1730106994904},{"title":"Cherish (My Love) (Remixes) (네이버 바이브 ─ 최신앨범 ─ 모든 앨범)","contents":"<!----><a data-v-78809b3d=\"\" href=\"/album/32236199\" class=\"title\"><span data-v-78809b3d=\"\" class=\"text_wrap\"><span data-v-78809b3d=\"\" id=\"32236199\" class=\"text\">Cherish (My Love) (Remixes)</span><!----><!----></span><span data-v-78809b3d=\"\" class=\"blind\">페이지로 이동</span></a><div data-v-78809b3d=\"\" class=\"artist\"><span data-v-78809b3d=\"\" class=\"artist_sub_inner\"><span><a href=\"/artist/8462145\" class=\"link_artist\"><span class=\"text\">아일릿(ILLIT)</span></a><!----></span></span><span data-v-78809b3d=\"\" class=\"blind\">아티스트명</span></div>","link":"https://vibe.naver.com/album/32236199","retrieved":1730106994904},{"title":"다시 사랑할 용기 (네이버 바이브 ─ 최신앨범 ─ 모든 앨범)","contents":"<!----><a data-v-78809b3d=\"\" href=\"/album/32235876\" class=\"title\"><span data-v-78809b3d=\"\" class=\"text_wrap\"><span data-v-78809b3d=\"\" id=\"32235876\" class=\"text\">다시 사랑할 용기</span><!----><!----></span><span data-v-78809b3d=\"\" class=\"blind\">페이지로 이동</span></a><div data-v-78809b3d=\"\" class=\"artist\"><span data-v-78809b3d=\"\" class=\"artist_sub_inner\"><span><a href=\"/artist/30552\" class=\"link_artist\"><span class=\"text\">우이경</span></a><!----></span></span><span data-v-78809b3d=\"\" class=\"blind\">아티스트명</span></div>","link":"https://vibe.naver.com/album/32235876","retrieved":1730106994904},{"title":"Loving You (네이버 바이브 ─ 최신앨범 ─ 모든 앨범)","contents":"<!----><a data-v-78809b3d=\"\" href=\"/album/32236073\" class=\"title\"><span data-v-78809b3d=\"\" class=\"text_wrap\"><span data-v-78809b3d=\"\" id=\"32236073\" class=\"text\">Loving You</span><!----><!----></span><span data-v-78809b3d=\"\" class=\"blind\">페이지로 이동</span></a><div data-v-78809b3d=\"\" class=\"artist\"><span data-v-78809b3d=\"\" class=\"artist_sub_inner\"><span><a href=\"/artist/3654851\" class=\"link_artist\"><span class=\"text\">LEEYOUNGWOONG</span></a><span>, </span></span><span><a href=\"/artist/8469190\" class=\"link_artist\"><span class=\"text\">sunoa(수노아)</span></a><!----></span></span><span data-v-78809b3d=\"\" class=\"blind\">아티스트명</span></div>","link":"https://vibe.naver.com/album/32236073","retrieved":1730106994904},{"title":"kin (네이버 바이브 ─ 최신앨범 ─ 모든 앨범)","contents":"<!----><a data-v-78809b3d=\"\" href=\"/album/32238775\" class=\"title\"><span data-v-78809b3d=\"\" class=\"text_wrap\"><span data-v-78809b3d=\"\" id=\"32238775\" class=\"text\">kin</span><!----><!----></span><span data-v-78809b3d=\"\" class=\"blind\">페이지로 이동</span></a><div data-v-78809b3d=\"\" class=\"artist\"><span data-v-78809b3d=\"\" class=\"artist_sub_inner\"><span><a href=\"/artist/6990145\" class=\"link_artist\"><span class=\"text\">비공정</span></a><!----></span></span><span data-v-78809b3d=\"\" class=\"blind\">아티스트명</span></div>","link":"https://vibe.naver.com/album/32238775","retrieved":1730106994904},{"title":"월간 AP - 2024년 10월 (네이버 바이브 ─ 최신앨범 ─ 모든 앨범)","contents":"<!----><a data-v-78809b3d=\"\" href=\"/album/32236564\" class=\"title\"><span data-v-78809b3d=\"\" class=\"text_wrap\"><span data-v-78809b3d=\"\" id=\"32236564\" class=\"text\">월간 AP - 2024년 10월</span><!----><!----></span><span data-v-78809b3d=\"\" class=\"blind\">페이지로 이동</span></a><div data-v-78809b3d=\"\" class=\"artist\"><span data-v-78809b3d=\"\" class=\"artist_sub_inner\"><span><a href=\"/artist/6340172\" class=\"link_artist\"><span class=\"text\">에이피 알케미(AP Alchemy)</span></a><!----></span></span><span data-v-78809b3d=\"\" class=\"blind\">아티스트명</span></div>","link":"https://vibe.naver.com/album/32236564","retrieved":1730106994904},{"title":"살아남아(remix) (네이버 바이브 ─ 최신앨범 ─ 모든 앨범)","contents":"<!----><a data-v-78809b3d=\"\" href=\"/album/32236525\" class=\"title\"><span data-v-78809b3d=\"\" class=\"text_wrap\"><span data-v-78809b3d=\"\" id=\"32236525\" class=\"text\">살아남아(remix)</span><!----><!----></span><span data-v-78809b3d=\"\" class=\"blind\">페이지로 이동</span></a><div data-v-78809b3d=\"\" class=\"artist\"><span data-v-78809b3d=\"\" class=\"artist_sub_inner\"><span><a href=\"/artist/3561376\" class=\"link_artist\"><span class=\"text\">Odd95</span></a><!----></span></span><span data-v-78809b3d=\"\" class=\"blind\">아티스트명</span></div>","link":"https://vibe.naver.com/album/32236525","retrieved":1730106994906},{"title":"산책 (네이버 바이브 ─ 최신앨범 ─ 모든 앨범)","contents":"<!----><a data-v-78809b3d=\"\" href=\"/album/32236187\" class=\"title\"><span data-v-78809b3d=\"\" class=\"text_wrap\"><span data-v-78809b3d=\"\" id=\"32236187\" class=\"text\">산책</span><!----><!----></span><span data-v-78809b3d=\"\" class=\"blind\">페이지로 이동</span></a><div data-v-78809b3d=\"\" class=\"artist\"><span data-v-78809b3d=\"\" class=\"artist_sub_inner\"><span><a href=\"/artist/22\" class=\"link_artist\"><span class=\"text\">김동률</span></a><!----></span></span><span data-v-78809b3d=\"\" class=\"blind\">아티스트명</span></div>","link":"https://vibe.naver.com/album/32236187","retrieved":1730020443597},{"title":"Over Each Other (네이버 바이브 ─ 최신앨범 ─ 모든 앨범)","contents":"<!----><a data-v-78809b3d=\"\" href=\"/album/32234535\" class=\"title\"><span data-v-78809b3d=\"\" class=\"text_wrap\"><span data-v-78809b3d=\"\" id=\"32234535\" class=\"text\">Over Each Other</span><!----><!----></span><span data-v-78809b3d=\"\" class=\"blind\">페이지로 이동</span></a><div data-v-78809b3d=\"\" class=\"artist\"><span data-v-78809b3d=\"\" class=\"artist_sub_inner\"><span><a href=\"/artist/4171\" class=\"link_artist\"><span class=\"text\">Linkin Park</span></a><!----></span></span><span data-v-78809b3d=\"\" class=\"blind\">아티스트명</span></div>","link":"https://vibe.naver.com/album/32234535","retrieved":1730085906133},{"title":"Goodbye (네이버 바이브 ─ 최신앨범 ─ 모든 앨범)","contents":"<!----><a data-v-78809b3d=\"\" href=\"/album/32236178\" class=\"title\"><span data-v-78809b3d=\"\" class=\"text_wrap\"><span data-v-78809b3d=\"\" id=\"32236178\" class=\"text\">Goodbye</span><!----><!----></span><span data-v-78809b3d=\"\" class=\"blind\">페이지로 이동</span></a><div data-v-78809b3d=\"\" class=\"artist\"><span data-v-78809b3d=\"\" class=\"artist_sub_inner\"><span><a href=\"/artist/340883\" class=\"link_artist\"><span class=\"text\">406호 프로젝트</span></a><!----></span></span><span data-v-78809b3d=\"\" class=\"blind\">아티스트명</span></div>","link":"https://vibe.naver.com/album/32236178","retrieved":1730085898453},{"title":"Everything Bagel (네이버 바이브 ─ 최신앨범 ─ 모든 앨범)","contents":"<!----><a data-v-78809b3d=\"\" href=\"/album/32238603\" class=\"title\"><span data-v-78809b3d=\"\" class=\"text_wrap\"><span data-v-78809b3d=\"\" id=\"32238603\" class=\"text\">Everything Bagel</span><!----><!----></span><span data-v-78809b3d=\"\" class=\"blind\">페이지로 이동</span></a><div data-v-78809b3d=\"\" class=\"artist\"><span data-v-78809b3d=\"\" class=\"artist_sub_inner\"><span><a href=\"/artist/3744613\" class=\"link_artist\"><span class=\"text\">차울</span></a><!----></span></span><span data-v-78809b3d=\"\" class=\"blind\">아티스트명</span></div>","link":"https://vibe.naver.com/album/32238603","retrieved":1730085898453},{"title":"illusion (네이버 바이브 ─ 최신앨범 ─ 모든 앨범)","contents":"<!----><a data-v-78809b3d=\"\" href=\"/album/32236182\" class=\"title\"><span data-v-78809b3d=\"\" class=\"text_wrap\"><span data-v-78809b3d=\"\" id=\"32236182\" class=\"text\">illusion</span><!----><!----></span><span data-v-78809b3d=\"\" class=\"blind\">페이지로 이동</span></a><div data-v-78809b3d=\"\" class=\"artist\"><span data-v-78809b3d=\"\" class=\"artist_sub_inner\"><span><a href=\"/artist/3069013\" class=\"link_artist\"><span class=\"text\">H3ATHR SUN(헤더썬)</span></a><!----></span></span><span data-v-78809b3d=\"\" class=\"blind\">아티스트명</span></div>","link":"https://vibe.naver.com/album/32236182","retrieved":1730085898461},{"title":"Duets (30th Anniversary) (네이버 바이브 ─ 최신앨범 ─ 모든 앨범)","contents":"<!----><a data-v-78809b3d=\"\" href=\"/album/32230857\" class=\"title\"><span data-v-78809b3d=\"\" class=\"text_wrap\"><span data-v-78809b3d=\"\" id=\"32230857\" class=\"text\">Duets (30th Anniversary)</span><!----><!----></span><span data-v-78809b3d=\"\" class=\"blind\">페이지로 이동</span></a><div data-v-78809b3d=\"\" class=\"artist\"><span data-v-78809b3d=\"\" class=\"artist_sub_inner\"><span><a href=\"/artist/8221\" class=\"link_artist\"><span class=\"text\">Andrea Bocelli</span></a><!----></span></span><span data-v-78809b3d=\"\" class=\"blind\">아티스트명</span></div>","link":"https://vibe.naver.com/album/32230857","retrieved":1730085906143},{"title":"Mom's Old Car (네이버 바이브 ─ 최신앨범 ─ 모든 앨범)","contents":"<!----><a data-v-78809b3d=\"\" href=\"/album/32228920\" class=\"title\"><span data-v-78809b3d=\"\" class=\"text_wrap\"><span data-v-78809b3d=\"\" id=\"32228920\" class=\"text\">Mom's Old Car</span><!----><!----></span><span data-v-78809b3d=\"\" class=\"blind\">페이지로 이동</span></a><div data-v-78809b3d=\"\" class=\"artist\"><span data-v-78809b3d=\"\" class=\"artist_sub_inner\"><span><a href=\"/artist/210688\" class=\"link_artist\"><span class=\"text\">Walk Off The Earth</span></a><!----></span></span><span data-v-78809b3d=\"\" class=\"blind\">아티스트명</span></div>","link":"https://vibe.naver.com/album/32228920","retrieved":1730085906143},{"title":"WHY ALWAYS ME? (네이버 바이브 ─ 최신앨범 ─ 모든 앨범)","contents":"<!----><a data-v-78809b3d=\"\" href=\"/album/32232686\" class=\"title\"><span data-v-78809b3d=\"\" class=\"text_wrap\"><span data-v-78809b3d=\"\" id=\"32232686\" class=\"text\">WHY ALWAYS ME?</span><!----><!----></span><span data-v-78809b3d=\"\" class=\"blind\">페이지로 이동</span></a><div data-v-78809b3d=\"\" class=\"artist\"><span data-v-78809b3d=\"\" class=\"artist_sub_inner\"><span><a href=\"/artist/3897832\" class=\"link_artist\"><span class=\"text\">Cochise</span></a><!----></span></span><span data-v-78809b3d=\"\" class=\"blind\">아티스트명</span></div>","link":"https://vibe.naver.com/album/32232686","retrieved":1730085906143},{"title":"Dystopia (네이버 바이브 ─ 최신앨범 ─ 모든 앨범)","contents":"<!----><a data-v-78809b3d=\"\" href=\"/album/32232144\" class=\"title\"><span data-v-78809b3d=\"\" class=\"text_wrap\"><span data-v-78809b3d=\"\" id=\"32232144\" class=\"text\">Dystopia</span><!----><!----></span><span data-v-78809b3d=\"\" class=\"blind\">페이지로 이동</span></a><div data-v-78809b3d=\"\" class=\"artist\"><span data-v-78809b3d=\"\" class=\"artist_sub_inner\"><span><a href=\"/artist/162840\" class=\"link_artist\"><span class=\"text\">ONE OK ROCK</span></a><!----></span></span><span data-v-78809b3d=\"\" class=\"blind\">아티스트명</span></div>","link":"https://vibe.naver.com/album/32232144","retrieved":1730085906143}]}